df_slots/__init__.py
df_slots/conditions.py
df_slots/forms.py
df_slots/handlers.py
df_slots/processing.py
df_slots/response.py
df_slots/root.py
df_slots/types.py
df_slots/utils.py
examples/__init__.py
examples/basic_example.py
examples/example_utils.py
examples/form_example.py
examples/generics_example.py
examples/handlers_example.py
tests/__init__.py
tests/conftest.py
tests/test_autoregister.py
tests/test_examples.py
tests/test_forms.py
tests/test_handlers.py
tests/test_slot_types.py
df_slots-0.1.0.dist-info/LICENSE
df_slots-0.1.0.dist-info/METADATA
df_slots-0.1.0.dist-info/WHEEL
df_slots-0.1.0.dist-info/top_level.txt
df_slots-0.1.0.dist-info/RECORD
