Metadata-Version: 2.1
Name: df-slots
Version: 0.1.0
Summary: **Dialog Flow Slots** is python module add-on for [Dialog Flow Framework](https://github.com/deepmipt/dialog_flow_framework), a free and open-source software stack for creating chatbots, released under the terms of Apache License 2.0.
Home-page: https://github.com/deepmipt/dialog_flow_slots
Author: Denis Kuznetsov
Author-email: kuznetsov.den.p@gmail.com
Keywords: chatbots,Dialog Flow Slots
Classifier: Development Status :: 2 - Pre-Alpha
Classifier: Intended Audience :: Developers
Classifier: Topic :: Software Development :: Build Tools
Classifier: License :: OSI Approved :: Apache Software License
Classifier: Operating System :: OS Independent
Classifier: Programming Language :: Python :: 3
Classifier: Programming Language :: Python :: 3.6
Classifier: Programming Language :: Python :: 3.7
Classifier: Programming Language :: Python :: 3.8
Classifier: Programming Language :: Python :: 3.9
Classifier: Programming Language :: Python :: 3 :: Only
Requires-Python: >=3.6, <4
License-File: LICENSE
Requires-Dist: df-engine (>=0.10.1)
Requires-Dist: df-generics (>=0.1.0)
